lockmyresource/__init__.py
lockmyresource/cli.py
lockmyresource/configfile.py
lockmyresource/core.py
lockmyresource/github25.png
lockmyresource/gui.py
lockmyresource/metainfo.py
lockmyresource/tableformatter.py
lockmyresource/userinfo.py
lockmyresource/util.py
lockmyresource-0.4.0.dist-info/AUTHORS.rst
lockmyresource-0.4.0.dist-info/LICENSE
lockmyresource-0.4.0.dist-info/METADATA
lockmyresource-0.4.0.dist-info/WHEEL
lockmyresource-0.4.0.dist-info/entry_points.txt
lockmyresource-0.4.0.dist-info/top_level.txt
lockmyresource-0.4.0.dist-info/RECORD
