Metadata-Version: 2.1
Name: lockmyresource
Version: 0.4.0
Summary: Coordinate locking resources for humans and machines using a simple sqlite file.
Home-page: https://github.com/szabopeter/lockmyresource
Author: Szabó Péter
Author-email: 1254135+szabopeter@users.noreply.github.com
License: GNU General Public License v3
Keywords: lockmyresource
Platform: UNKNOWN
Classifier: Development Status :: 2 - Pre-Alpha
Classifier: Intended Audience :: Developers
Classifier: License :: OSI Approved :: GNU General Public License v3 (GPLv3)
Classifier: Natural Language :: English
Classifier: Programming Language :: Python :: 3
Classifier: Programming Language :: Python :: 3.5
Classifier: Programming Language :: Python :: 3.6
Classifier: Programming Language :: Python :: 3.7
Classifier: Programming Language :: Python :: 3.8
Requires-Python: >=3.5
